[
    {
      "model": "sellers.seller",
      "pk": 1,
      "fields": {
        "store_name": "test_store",
        "website": "https://example.test",
        "user": 3
      }
    },
    {
      "model": "sellers.seller",
      "pk": 2,
      "fields": {
        "store_name": "other_store",
        "website": "https://other.test",
        "user": 2
      }
    },
    {
      "model": "sellers.seller",
      "pk": 3,
      "fields": {
        "store_name": "store_with_product",
        "website": "https://product-store.test",
        "user": 4
      }
    }
]